ipmerge-0.1.1.dist-info/METADATA
ipmerge-0.1.1.dist-info/WHEEL
ipmerge-0.1.1.dist-info/entry_points.txt
ipmerge-0.1.1.dist-info/licenses/LICENSE
ipmerge/__init__.py
ipmerge/__main__.py
ipmerge/__version__.py
ipmerge/address/__init__.py
ipmerge/address/address.py
ipmerge/address/address_block.py
ipmerge/address/exceptions.py
ipmerge/address/ipv4.py
ipmerge/address/ipv6.py
ipmerge/ipmerge.py
ipmerge/parameters.py
ipmerge-0.1.1.dist-info/RECORD
