Metadata-Version: 2.1
Name: IPMerge
Version: 0.1.1
Summary: Merge CIDR blocks of IPv4 and IPv6 addresses
Author-Email: Vojtech Kursa <it.vojtechkursa@gmail.com>
License: MIT
Classifier: Environment :: Console
Classifier: Programming Language :: Python :: 3
Classifier: Programming Language :: Python :: 3.10
Classifier: Programming Language :: Python :: 3.11
Classifier: Programming Language :: Python :: 3.12
Classifier: Programming Language :: Python :: 3.13
Classifier: License :: OSI Approved :: MIT License
Classifier: Operating System :: OS Independent
Classifier: Intended Audience :: System Administrators
Classifier: Topic :: Utilities
Classifier: Topic :: System :: Networking
Classifier: Topic :: Text Processing :: General
Classifier: Natural Language :: English
Classifier: Typing :: Typed
Requires-Python: >=3.10
Provides-Extra: tests
Requires-Dist: pytest>=8.2.0; extra == "tests"
